LICENSE.txt
README.md
setup.py
Lazy_pratik_model/__init__.py
Lazy_pratik_model.egg-info/PKG-INFO
Lazy_pratik_model.egg-info/SOURCES.txt
Lazy_pratik_model.egg-info/dependency_links.txt
Lazy_pratik_model.egg-info/requires.txt
Lazy_pratik_model.egg-info/top_level.txt