Metadata-Version: 2.1
Name: Lazy-pratik-model
Version: 0.0.1
Summary: This package directly gives you output performance on different models
Home-page: 
Author: pratik
Author-email: pratikvdatey@gmail.com
License: MIT
Keywords: Lazy_pratik_model
Classifier: Intended Audience :: Education
Classifier: Operating System :: Microsoft :: Windows :: Windows 10
Classifier: License :: OSI Approved :: MIT License
Classifier: Programming Language :: Python :: 3
License-File: LICENSE.txt
